llm_proxy/__init__.py
llm_proxy/__main__.py
llm_proxy/app.py
llm_proxy/auth.py
llm_proxy/config.py
llm_proxy/data.py
llm_proxy/fastapi_server.py
llm_proxy/llm.py
llm_proxy/request_data.py
llm_proxy/sender.py
llm_proxy/settings.py
llm_proxy/utils.py
llm_proxy/param/__init__.py
llm_proxy/param/common.py
llm_proxy/param/openai.py
llm_proxy/param/volcengine.py
llm_proxy/provider/__init__.py
llm_proxy/provider/openai_provider.py
llm_proxy/provider/provider.py
llm_proxy/servicer/__init__.py
llm_proxy/servicer/claude.py
llm_proxy/servicer/servicer.py
llm_proxypy-0.0.13.dist-info/licenses/LICENSE
llm_proxypy-0.0.13.dist-info/METADATA
llm_proxypy-0.0.13.dist-info/WHEEL
llm_proxypy-0.0.13.dist-info/top_level.txt
llm_proxypy-0.0.13.dist-info/RECORD
