Metadata-Version: 2.4
Name: llm-proxypy
Version: 0.0.13
Summary: llm proxy server
Author-email: shlll <shlll7347@gmail.com>
Requires-Python: >=3.9
License-File: LICENSE
Requires-Dist: pyjwt
Requires-Dist: pyyaml
Requires-Dist: uvicorn
Requires-Dist: gunicorn
Requires-Dist: tiktoken
Requires-Dist: shutilspy
Requires-Dist: pydantic-settings>=2.0.3
Provides-Extra: requests
Requires-Dist: requests; extra == "requests"
Provides-Extra: httpx
Requires-Dist: httpx; extra == "httpx"
Provides-Extra: aiohttp
Requires-Dist: aiohttp; extra == "aiohttp"
Provides-Extra: fastapi
Requires-Dist: fastapi; extra == "fastapi"
Dynamic: license-file
